Metadata-Version: 2.4
Name: opsmate-provider-groq
Version: 0.1.1a0
Summary: Groq provider for opsmate
Author-email: Jingkai He <jingkai@hey.com>
License: MIT License
License-File: LICENSE
Requires-Python: <4.0,>=3.10
Requires-Dist: groq>=0.22.0
Requires-Dist: opsmate
